flexidb/__init__.py
flexidb/factory.py
flexidb/interface.py
flexidb/mongodb.py
flexidb/mysql.py
flexidb/postgresql.py
flexidb/redis.py
flexidb/sqlite.py
flexidb-1.0.0.dist-info/METADATA
flexidb-1.0.0.dist-info/WHEEL
flexidb-1.0.0.dist-info/top_level.txt
flexidb-1.0.0.dist-info/RECORD
